lenscraft/__init__.py
lenscraft/__main__.py
lenscraft/_version.py
lenscraft/app.py
lenscraft/cli.py
lenscraft/gabor.py
lenscraft/image.py
lenscraft/utils.py
lenscraft/assets/CornerTemplate.png
lenscraft/editor/__init__.py
lenscraft/node/__init__.py
lenscraft/node/attributes.py
lenscraft/node/editor.py
lenscraft/node/nodes/__init__.py
lenscraft/node/nodes/canny.py
lenscraft/node/nodes/img_library.py
lenscraft/node/nodes/minmax.py
lenscraft/node/nodes/show_feature.py
lenscraft/node/nodes/template.py
lenscraft/node/nodes/texture.py
lenscraft/node/nodes/threshold.py
lenscraft/texture/__init__.py
lenscraft/texture/model.py
lenscraft/texture/tool.py
lenscraft-1.2.0.dist-info/LICENSE
lenscraft-1.2.0.dist-info/METADATA
lenscraft-1.2.0.dist-info/WHEEL
lenscraft-1.2.0.dist-info/entry_points.txt
lenscraft-1.2.0.dist-info/top_level.txt
lenscraft-1.2.0.dist-info/RECORD
